Warrior_pytho_3-0.0.1.data/scripts/warriorpy.py
Warrior_pytho_3-0.0.1.dist-info/METADATA
Warrior_pytho_3-0.0.1.dist-info/RECORD
Warrior_pytho_3-0.0.1.dist-info/WHEEL
Warrior_pytho_3-0.0.1.dist-info/top_level.txt
warriorpy/__init__.py
warriorpy/runner.py
warriorpy/towers/beginner/__init__.py
warriorpy/towers/beginner/level_001.py
warriorpy/towers/beginner/level_002.py
warriorpy/towers/beginner/level_003.py
warriorpy/towers/beginner/level_004.py
warriorpy/towers/beginner/level_005.py
warriorpy/towers/beginner/level_006.py
warriorpy/towers/beginner/level_007.py
warriorpy/towers/beginner/level_008.py
warriorpy/towers/beginner/level_009.py
warriorpy/towers/intermediate/__init__.py
warriorpy/towers/intermediate/level_001.py
warriorpy/towers/intermediate/level_002.py
warriorpy/towers/intermediate/level_003.py
warriorpy/towers/intermediate/level_004.py
warriorpy/towers/intermediate/level_005.py
warriorpy/towers/intermediate/level_006.py
warriorpy/towers/intermediate/level_007.py
warriorpy/towers/intermediate/level_008.py
warriorpy/towers/intermediate/level_009.py
warriorpy/warriorpyAbilities/src/__init__.py
warriorpy/warriorpyAbilities/src/attack.py
warriorpy/warriorpyAbilities/src/base.py
warriorpy/warriorpyAbilities/src/bind.py
warriorpy/warriorpyAbilities/src/detonate.py
warriorpy/warriorpyAbilities/src/direction_of.py
warriorpy/warriorpyAbilities/src/direction_of_stairs.py
warriorpy/warriorpyAbilities/src/distance_of.py
warriorpy/warriorpyAbilities/src/explode.py
warriorpy/warriorpyAbilities/src/feel.py
warriorpy/warriorpyAbilities/src/health.py
warriorpy/warriorpyAbilities/src/listen.py
warriorpy/warriorpyAbilities/src/look.py
warriorpy/warriorpyAbilities/src/pivot.py
warriorpy/warriorpyAbilities/src/rescue.py
warriorpy/warriorpyAbilities/src/rest.py
warriorpy/warriorpyAbilities/src/shoot.py
warriorpy/warriorpyAbilities/src/walk.py
warriorpy/warriorpyCli/src/game.py
warriorpy/warriorpyCli/src/player_generator.py
warriorpy/warriorpyCli/src/profile.py
warriorpy/warriorpyCli/src/ui/terminal_screen_size.py
warriorpy/warriorpyCli/src/ui/test_terminal_screen_size..py
