Metadata-Version: 2.1
Name: Warrior-pytho-3
Version: 0.0.1
Summary: An exciting game of programming and Artificial Intelligence
Home-page: https://github.com/justdvnsh/warriorpy
Author: Divyansh Dwivedi
Author-email: justdvnsh2208@gmail.com
License: MIT
Keywords: python ruby javascript rubywarrior warriorjs warriorpy
Platform: UNKNOWN
Classifier: Programming Language :: Python
Classifier: License :: OSI Approved :: MIT License
Classifier: Development Status :: 3 - Alpha
Requires-Dist: jinja2
